{
  "$schema": "https://schema.management.azure.com/schemas/2019-04-01/deploymentParameters.json#",
  "contentVersion": "1.0.0.0",
  "metadata": {
    "template": "modules/azure/features/Lighthouse/deploy.bicep"
  },
  "parameters": {
    "mspOfferName": {
      "value": "InSpark - Managed Cloud"
    },
    "mspOfferDescription": {
      "value": "InSpark - Managed Cloud"
    },
    "managedByTenantId": {
      "value": "2b55fa1c-0add-4120-a8e4-9987abf4d504"
    },
    "authorizations": {
      "value": [
        {
          "principalId": "5257e377-c963-4fd4-ac7f-8052081bfdb4",
          "principalIdDisplayName": "Lighthouse – MS Infrastructure – Reader",
          "roleDefinitionId": "acdd72a7-3385-48ef-bd42-f606fba81ae7"
        }
      ]
    },
    "eligibleAuthorizations": {
      "value": [
        {
          "justInTimeAccessPolicy": {
            "multiFactorAuthProvider": "Azure",
            "maximumActivationDuration": "PT8H"
          },
          "principalId": "b73501a7-b4c7-44fe-bb2f-ab2c800e3a98",
          "principalIdDisplayName": "Lighthouse – MS Infrastructure – Contributor",
          "roleDefinitionId": "b24988ac-6180-42a0-ab88-20f7382dd24c"
        }
      ]
    }
  }
}
